README.md
setup.py
timeout_tttttttttt/__init__.py
timeout_tttttttttt/tm.py
timeout_tttttttttt.egg-info/PKG-INFO
timeout_tttttttttt.egg-info/SOURCES.txt
timeout_tttttttttt.egg-info/dependency_links.txt
timeout_tttttttttt.egg-info/top_level.txt